g2c/__init__.py
g2c/main.py
g2c/packaged_data/.g2c_cache
g2c/packaged_data/g2c_cache
g2c-0.4.3.dist-info/METADATA
g2c-0.4.3.dist-info/WHEEL
g2c-0.4.3.dist-info/entry_points.txt
g2c-0.4.3.dist-info/licenses/LICENSE
g2c-0.4.3.dist-info/RECORD
