Metadata-Version: 2.4
Name: g2c
Version: 0.4.3
Summary: g2c is a python script to convert Gremlin query to Cypher query with OpenAI API
Project-URL: Homepage, https://github.com/rioriost/homebrew-g2c
Project-URL: Issues, https://github.com/rioriost/homebrew-g2c/issues
Author-email: Rio Fujita <rifujita@microsoft.com>
License: MIT License
License-File: LICENSE
Requires-Python: >=3.11
Requires-Dist: openai>=1.64.0
Requires-Dist: psycopg[binary,pool]>=3.2.5
